parsix_gazinform/__init__.py
parsix_gazinform-1.1.dist-info/METADATA
parsix_gazinform-1.1.dist-info/RECORD
parsix_gazinform-1.1.dist-info/WHEEL
parsix_gazinform-1.1.dist-info/top_level.txt
